anime_or_not/__init__.py
anime_or_not/anime_or_not_model.onnx
anime_or_not/predict.py
anime_or_not-0.0.7.dist-info/METADATA
anime_or_not-0.0.7.dist-info/WHEEL
anime_or_not-0.0.7.dist-info/top_level.txt
anime_or_not-0.0.7.dist-info/RECORD
