Metadata-Version: 2.1
Name: anime-or-not
Version: 0.0.7
Summary: Classifies if an image is "anime" or not
Home-page: UNKNOWN
Author: LaihoE
License: UNKNOWN
Platform: UNKNOWN
Requires-Dist: onnxruntime
Requires-Dist: Pillow
Requires-Dist: torchvision
Requires-Dist: torch
